adder32/full_adder.v
module full_adder (
  input wire A, // 1 input bit
  input wire B, // 1 input bit
  input wire carry_in, // carry in bit
  output wire sum_bit,
  output wire carry_out
);

assign sum_bit = A^B^carry_in;
assign carry_out = A&B | B&carry_in | A&carry_in; // if any two are turned on

endmodule

adder32/full_adder_tb.v
module tb_full_adder;

  reg A, B, carry_in;
  wire sum_bit, carry_out;

  // Instantiate the full_adder module
  full_adder uut (
      .A(A),
      .B(B),
      .carry_in(carry_in),
      .sum_bit(sum_bit),
      .carry_out(carry_out)
  );

  // Testbench logic
  initial begin
    // Open the waveform dump file
    $dumpfile("full_adder.vcd");
    $dumpvars(0, tb_full_adder);
    
    // Test case 1: A=0, B=0, carry_in=0
    A = 0; B = 0; carry_in = 0;
    #10; // Delay to see the result in the waveform

    // Test case 2: A=0, B=0, carry_in=1
    carry_in = 1;
    #10;

    // Test case 3: A=0, B=1, carry_in=0
    B = 1; carry_in = 0;
    #10;

    // A=0, B=1, C=1
    carry_in = 1;
    #10

    // A=1, B=0, cin=0
    A = 1; B = 0; carry_in = 0;
    #10

    // Test case 2: A=1, B=0, carry_in=1
    carry_in = 1;
    #10;

    // Test case 3: A=1, B=1, carry_in=0
    B = 1; carry_in = 0;
    #10;

    // Test case 8: A=1, B=1, carry_in=1
    carry_in = 1;
    #10;

    $finish;  // End the simulation
  end
endmodule

adder32/full_adder.vcd
$date
	Tue Oct 31 20:02:02 2023
$end
$version
	Icarus Verilog
$end
$timescale
	1s
$end
$scope module tb_full_adder $end
$var wire 1 ! sum_bit $end
$var wire 1 " carry_out $end
$var reg 1 # A $end
$var reg 1 $ B $end
$var reg 1 % carry_in $end
$scope module uut $end
$var wire 1 # A $end
$var wire 1 $ B $end
$var wire 1 % carry_in $end
$var wire 1 " carry_out $end
$var wire 1 ! sum_bit $end
$upscope $end
$upscope $end
$enddefinitions $end
$comment Show the parameter values. $end
$dumpall
$end
#0
$dumpvars
0%
0$
0#
0"
0!
$end
#10
1!
1%
#20
0%
1$
#30
1"
0!
1%
#40
0"
1!
0%
0$
1#
#50
1"
0!
1%
#60
0%
1$
#70
1!
1%
