uart/transmitter.sv
module transmitter(
    input logic clk,
    input logic reset,
    input logic tx_start,
    input logic [7:0] data_in,
    output logic tx_line,
    output logic tx_busy
);

typedef enum {
    Idle, Start, Data, Stop, Cleanup
} states_t;

// 5 states so 3 bits needed
reg [2:0] state, next_state;
// 8 bits for counter
reg [2:0] Dctr;



// reset: is sequential signal, used to immediately halt and return to idle
// procedural block that executes every clock cycle
always @(posedge clk or posedge reset) begin
    if(reset) begin
        state <= Idle;
        // next_state <= Idle;
        Dctr <= 3'b000;
    end else begin
        // state <= next_state;
    end

    if (state == Start) begin
        if (clk) begin
            state = Data;
            tx_line = data_in[Dctr];
        end
        // else next_state = Start;
    end
    else if (state == Data) begin
        // tx_line = data_in[Dctr]; // serially transmitting data
        if (Dctr == 3'b111) begin
            state = Stop;
            tx_line = 1;
        end else begin
            state = Data;
            Dctr = Dctr + 1;
            tx_line = data_in[Dctr];
        end
    end
    else if (state == Stop) begin
        if (clk) state = Idle;
        // else next_state = Stop;
    end
end

// sensitivity list contains all the combinational logic inputs
always @(state, tx_start, Dctr) begin 
    case(state)
        Idle: begin
            tx_line = 1;
            tx_busy = 0;
            if (tx_start) begin
                state = Start;
                tx_line = 0; // Start bit
                tx_busy = 1;
            end
            // else next_state = Idle;
        end
        // Start: begin
        //     tx_line = 0; // Start bit
        //     tx_busy = 1;
        //     if (clk) next_state = Data;
        //     // else next_state = Start;
        // end
        // Data: begin
        //     tx_line = data_in[Dctr]; // serially transmitting data
        //     if (Dctr == 3'b111) begin
        //         next_state = Stop;
        //     end else begin
        //         next_state = Data;
        //         Dctr = Dctr + 1;
        //     end
        // end
        // Stop: begin
        //     tx_line = 1;
        //     if (clk) next_state = Idle;
        //     // else next_state = Stop;
        // end
    endcase
end

endmodule


// // reset: is sequential signal, used to immediately halt and return to idle
// // procedural block that executes every clock cycle
// always @(posedge clk or posedge reset) begin
//     if(reset) begin
//         state <= Idle;
//         next_state <= Idle;
//         Dctr <= 3'b000;
//     end else begin
//         state <= next_state;
//     end

//     if (state == Start) begin
//         tx_line = 0; // Start bit
//         tx_busy = 1;
//         if (clk) next_state = Data;
//         // else next_state = Start;
//     end
//     if (state == Data) begin
//         tx_line = data_in[Dctr]; // serially transmitting data
//         if (Dctr == 3'b111) begin
//             next_state = Stop;
//         end else begin
//             next_state = Data;
//             Dctr = Dctr + 1;
//         end
//     end
//     if (state == Stop) begin
//         tx_line = 1;
//         if (clk) next_state = Idle;
//         // else next_state = Stop;
//     end
// end

// // sensitivity list contains all the combinational logic inputs
// always @(state, tx_start, Dctr) begin 
//     case(state)
//         Idle: begin
//             tx_line = 1;
//             tx_busy = 0;
//             if (tx_start) next_state = Start;
//             // else next_state = Idle;
//         end
//         // Start: begin
//         //     tx_line = 0; // Start bit
//         //     tx_busy = 1;
//         //     if (clk) next_state = Data;
//         //     // else next_state = Start;
//         // end
//         // Data: begin
//         //     tx_line = data_in[Dctr]; // serially transmitting data
//         //     if (Dctr == 3'b111) begin
//         //         next_state = Stop;
//         //     end else begin
//         //         next_state = Data;
//         //         Dctr = Dctr + 1;
//         //     end
//         // end
//         // Stop: begin
//         //     tx_line = 1;
//         //     if (clk) next_state = Idle;
//         //     // else next_state = Stop;
//         // end
//     endcase
// end

// endmodule

uart/transmitter_tb.sv
// `timescale 1ns/1ps

module tb_transmitter;

    localparam CLK_PERIOD = 10; // Clock period in ns

    reg clk;          // Clock signal
    reg reset;        // Reset signal
    reg tx_start;     // Transmission start signal
    reg [7:0] data_in; // Input data
    wire tx_line;     // Transmit line output from UUT (Unit Under Test)
    wire tx_busy;     // Transmit busy signal output from UUT

    // Instantiate the transmitter
    transmitter UUT (
        .clk(clk),
        .reset(reset),
        .tx_start(tx_start),
        .data_in(data_in),
        .tx_line(tx_line),
        .tx_busy(tx_busy)
    );

    initial begin
        $dumpfile("transmitter.vcd");  // For waveform viewing
        $dumpvars(0, tb_transmitter);

        // Initialize signals
        clk = 0;
        reset = 1;
        tx_start = 0;
        data_in = 8'b00000000;

        // Reset sequence
        // We wait for 5ns because initially clk is 0, half cycle is 5ns, so rising edge we can switch 
        // states
        #(CLK_PERIOD/2) reset = 0;

        // Transmit data sequence
        // LSB will be transmitted first
        data_in = 8'b11001101;  // Change data input
        tx_start = 1;          // Start the transmission
        
        #(CLK_PERIOD)
        tx_start = 0;          // Release the tx_start signal in 10s 

        // Wait and observe the outputs
        #200;
        
        // Repeat transmission with different data to verify
        // #10 data_in = 8'b10101010;  
        // #10 tx_start = 1;          
        // #10 tx_start = 0;          

        // // Wait and observe
        // #200;

        $finish;  // End the simulation
    end

    // Clock generation
    always #(CLK_PERIOD/2) clk = ~clk;  

endmodule

uart/transmitter.vcd
$date
	Tue Nov  7 16:01:35 2023
$end
$version
	Icarus Verilog
$end
$timescale
	1s
$end
$scope module tb_transmitter $end
$var wire 1 ! tx_line $end
$var wire 1 " tx_busy $end
$var parameter 32 # CLK_PERIOD $end
$var reg 1 $ clk $end
$var reg 8 % data_in [7:0] $end
$var reg 1 & reset $end
$var reg 1 ' tx_start $end
$scope module UUT $end
$var wire 1 $ clk $end
$var wire 8 ( data_in [7:0] $end
$var wire 1 & reset $end
$var wire 1 ' tx_start $end
$var reg 3 ) Dctr [2:0] $end
$var reg 3 * next_state [2:0] $end
$var reg 3 + state [2:0] $end
$var reg 1 " tx_busy $end
$var reg 1 ! tx_line $end
$upscope $end
$upscope $end
$enddefinitions $end
$comment Show the parameter values. $end
$dumpall
b1010 #
$end
#0
$dumpvars
b0 +
b0 *
b0 )
b0 (
0'
1&
b0 %
0$
0"
1!
$end
#5
1"
0!
b1 +
b10 *
1$
1'
b11001101 %
b11001101 (
0&
#10
0$
#15
b10 +
1$
0'
#20
0$
#25
b1 )
1!
1$
#30
0$
#35
b10 )
0!
1$
#40
0$
#45
b11 )
1!
1$
#50
0$
#55
b100 )
1$
#60
0$
#65
b101 )
0!
1$
#70
0$
#75
b110 )
1$
#80
0$
#85
b111 )
1!
1$
#90
0$
#95
b11 *
1$
#100
0$
#105
b0 *
b11 +
1$
#110
0$
#115
0"
b0 +
1$
