uart/receiver.sv
module receiver (
    input wire rx_clk, // Oversampling clock
    input wire rx_serial, // Serial input from TX
    input wire reset,
    output reg [7:0] rx_data, // Received byte
    output reg rx_done, // High when a byte is received
    output reg framing_error
);
    // Define states
    typedef enum {
        Idle, Start, Rcv_Data, Stop, Error
    } states_t;

    reg [2:0] state = Idle; // Current state
    reg [3:0] bit_index = 3'd0; // Bit index of the data being received
    reg [3:0] sample_count = 4'd0; // Counts the number of samples for each bit
    reg [7:0] shift_reg = 8'd0; // Shift register to temporarily hold the incoming bits

    // Number of samples per bit is 16
    localparam integer SAMPLES_PER_BIT = 15;
    // Halfway point to sample a bit, you might adjust this for better performance
    localparam integer SAMPLE_POINT = 7;

    // State machine
    always @(posedge rx_clk or posedge reset) begin
        if (reset) begin
            framing_error <= 0;
            state <= Idle;
            rx_data <= 8'd0;
            rx_done <= 1'b0;
            bit_index <= 3'd0;
            sample_count <= 4'd0;
            shift_reg <= 8'd0;
        end else begin
            case (state)
                Idle: begin
                    if (!rx_serial) begin // Detect start bit (usually low)
                        state <= Start;
                        sample_count <= 4'd0; // Start sampling
                    end
                end
                Start: begin
                  sample_count <= sample_count + 1;
                  if (sample_count == SAMPLE_POINT) begin
                      if (!rx_serial) begin // Confirm start bit
                          // dont reset because it will be at 7 so we sample 8 more bits to get 
                          // 15th bit which is middle point of first bit of data
                          state <= Rcv_Data;
                          bit_index <= 3'd0;
                          sample_count <= 4'd0;
                      end else begin
                          state <= Idle;
                      end
                  end
                end
                Rcv_Data: begin
                  sample_count <= sample_count + 1;
                  // If we reach 16 bits we set bit into reg
                  if (sample_count == SAMPLES_PER_BIT) begin
                      shift_reg[bit_index] <= rx_serial; // Sample the data bit
                      bit_index <= bit_index + 1;
                      sample_count <= 4'd0;
                      if (bit_index == 3'd7) begin
                          sample_count <= 4'd0; // Reset sample count
                          state <= Stop;
                      end
                  end
                end
                Stop: begin
                  sample_count <= sample_count + 1;
                    // If we reach 7 bits we finish.
                    if (sample_count == SAMPLES_PER_BIT) begin
                        if (rx_serial) begin // Verify stop bit
                            rx_data <= shift_reg;
                            rx_done <= 1'b1;
                            state <= Idle;
                            framing_error <= 0;
                        end else begin
                            state <= Error;
                        end
                    end
                end
                Error: begin
                    // Error handling here
                    state <= Idle; // For now, simply return to Idle
                    framing_error <= 1;
                end
            endcase
        end
    end
endmodule

uart/transmitter.sv
module transmitter(
    input logic clk,
    input logic reset,
    input logic tx_start,
    input logic [7:0] data_in,
    output logic tx_line,
    output logic tx_busy
);

typedef enum {
    Idle, Start, Data, Stop, Cleanup
} states_t;

// 5 states so 3 bits needed
reg [2:0] state, next_state;
// 8 bits for counter
reg [2:0] Dctr;



// reset: is sequential signal, used to immediately halt and return to idle
// procedural block that executes every clock cycle
always @(posedge clk or posedge reset) begin
    if(reset) begin
        state <= Idle;
        // next_state <= Idle;
        Dctr <= 3'b000;
    end else begin
        // state <= next_state;
    end

    if (state == Start) begin
        if (clk) begin
            state = Data;
            tx_line = data_in[Dctr];
        end
        // else next_state = Start;
    end
    else if (state == Data) begin
        // tx_line = data_in[Dctr]; // serially transmitting data
        if (Dctr == 3'b111) begin
            state = Stop;
            tx_line = 1;
        end else begin
            state = Data;
            Dctr = Dctr + 1;
            tx_line = data_in[Dctr];
        end
    end
    else if (state == Stop) begin
        if (clk) state = Idle;
        // else next_state = Stop;
    end
end

// sensitivity list contains all the combinational logic inputs
always @(state, tx_start, Dctr) begin 
    case(state)
        Idle: begin
            tx_line = 1;
            tx_busy = 0;
            if (tx_start) begin
                state = Start;
                tx_line = 0; // Start bit
                tx_busy = 1;
            end
            // else next_state = Idle;
        end
        // Start: begin
        //     tx_line = 0; // Start bit
        //     tx_busy = 1;
        //     if (clk) next_state = Data;
        //     // else next_state = Start;
        // end
        // Data: begin
        //     tx_line = data_in[Dctr]; // serially transmitting data
        //     if (Dctr == 3'b111) begin
        //         next_state = Stop;
        //     end else begin
        //         next_state = Data;
        //         Dctr = Dctr + 1;
        //     end
        // end
        // Stop: begin
        //     tx_line = 1;
        //     if (clk) next_state = Idle;
        //     // else next_state = Stop;
        // end
    endcase
end

endmodule


// // reset: is sequential signal, used to immediately halt and return to idle
// // procedural block that executes every clock cycle
// always @(posedge clk or posedge reset) begin
//     if(reset) begin
//         state <= Idle;
//         next_state <= Idle;
//         Dctr <= 3'b000;
//     end else begin
//         state <= next_state;
//     end

//     if (state == Start) begin
//         tx_line = 0; // Start bit
//         tx_busy = 1;
//         if (clk) next_state = Data;
//         // else next_state = Start;
//     end
//     if (state == Data) begin
//         tx_line = data_in[Dctr]; // serially transmitting data
//         if (Dctr == 3'b111) begin
//             next_state = Stop;
//         end else begin
//             next_state = Data;
//             Dctr = Dctr + 1;
//         end
//     end
//     if (state == Stop) begin
//         tx_line = 1;
//         if (clk) next_state = Idle;
//         // else next_state = Stop;
//     end
// end

// // sensitivity list contains all the combinational logic inputs
// always @(state, tx_start, Dctr) begin 
//     case(state)
//         Idle: begin
//             tx_line = 1;
//             tx_busy = 0;
//             if (tx_start) next_state = Start;
//             // else next_state = Idle;
//         end
//         // Start: begin
//         //     tx_line = 0; // Start bit
//         //     tx_busy = 1;
//         //     if (clk) next_state = Data;
//         //     // else next_state = Start;
//         // end
//         // Data: begin
//         //     tx_line = data_in[Dctr]; // serially transmitting data
//         //     if (Dctr == 3'b111) begin
//         //         next_state = Stop;
//         //     end else begin
//         //         next_state = Data;
//         //         Dctr = Dctr + 1;
//         //     end
//         // end
//         // Stop: begin
//         //     tx_line = 1;
//         //     if (clk) next_state = Idle;
//         //     // else next_state = Stop;
//         // end
//     endcase
// end

// endmodule

uart/baud_rate_generator.sv
module baud_rate_generator #(
    parameter CLOCK_RATE = 100000000, // board internal clock (def == 100MHz)
    parameter BAUD_RATE = 9600
)(
    input wire clk,          // System clock
    output reg clk_tx,       // Transmitter clock
    output reg clk_rcvr,       // Receiver clock
    input wire reset         // Active-high reset
);
    // PCLK / Baud rate = 1,000,000 / 9600 ≈ 104.17
    // parameter DIVIDER = 104;  // Example: for 9600 baud with a 1MHz clock
    // parameter DIVIDER_16 = 6; // 104 / 16 = 6.5, so 6 is the closest integer
    parameter MAX_RATE_TX = CLOCK_RATE / (BAUD_RATE*100);
    parameter MAX_RATE_RX = MAX_RATE_TX / 16; // 16x oversample
    parameter RX_CNT_WIDTH = $clog2(MAX_RATE_RX);
    parameter TX_CNT_WIDTH = $clog2(MAX_RATE_TX);
    reg [TX_CNT_WIDTH - 1:0] counter_tx = 0;  
    reg [RX_CNT_WIDTH - 1:0] counter_rcvr = 0;

    initial begin
      clk_tx = 1'b0;
      clk_rcvr = 1'b0;
    end

    always @(posedge clk or posedge reset) begin
        if (reset) begin
            counter_tx <= 7'd0;
            counter_rcvr <= 7'd0;
            clk_tx <= 0;
            clk_rcvr <= 0;
        end else if (counter_tx == MAX_RATE_TX[TX_CNT_WIDTH-1:0]) begin
            counter_tx <= 7'd0;
            clk_tx <= ~clk_tx;  // Toggle the transmitter clock
        end else if (counter_rcvr == MAX_RATE_RX[RX_CNT_WIDTH-1:0]) begin
            counter_rcvr <= 7'd0;
            clk_rcvr <= ~clk_rcvr;  // Toggle the receiver clock
        end else begin
            counter_tx <= counter_tx + 1'b1;
            counter_rcvr <= counter_rcvr + 1'b1;
        end
    end

endmodule

uart/uart.sv
// `timescale 1ns/1ps

module uart #(
    parameter CLOCK_RATE = 100000000, // board internal clock (def == 100MHz)
    parameter BAUD_RATE = 9600
)(
  input wire pclk, // system clock
  input wire reset,
  input wire tx_start,       // Signal to start transmission
  input wire [7:0] data_in,  // Data to be transmitted
  output wire tx_line,       // UART transmission line
  output wire tx_busy,       // UART is busy transmitting
  input wire rx_serial,  // External signal received by UART
  output wire [7:0] rx_data, // Data received by UART
  output wire rx_done,        // UART has received a byte
  output wire framing_error  // Framing error
);

  // Common clock for both transmitter and receiver
  reg clk_tx;
  reg clk_rcvr;

  // Receiver register 
  // wire [7:0] rx_data; // Data received by UART

  baud_rate_generator #(
    .CLOCK_RATE(CLOCK_RATE),
    .BAUD_RATE(BAUD_RATE)
  ) baud_gen (
    .clk(pclk),
    .clk_tx(clk_tx),
    .clk_rcvr(clk_rcvr),
    .reset(reset)
  );

  // Instantiate the transmitter
  transmitter tx_uut (
      .clk(clk_tx),
      .reset(reset),
      .tx_start(tx_start),
      .data_in(data_in),
      .tx_line(tx_line),
      .tx_busy(tx_busy)
  );

  // Instantiate the receiver
  receiver rx_uut (
      .rx_clk(clk_rcvr), // The receiver clock is 16 times faster than the transmitter clock
      .rx_serial(rx_serial),
      .reset(reset),
      .rx_data(rx_data),
      .rx_done(rx_done),
      .framing_error(framing_error)
  );

endmodule

uart/uart_tb.sv
`timescale 1ns/1ps

module uart_tb;

  reg pclk; // System clock
  reg reset; // Reset signal
  reg tx_start; // Signal to start transmission
  reg [7:0] data_in; // Data to be transmitted
  wire tx_line; // UART transmission line
  wire tx_busy; // UART is busy transmitting
  reg rx_serial; // External signal received by UART
  wire [7:0] rx_data; // Data received by UART
  wire rx_done; // UART has received a byte

  // Instantiate the UART module
  uart uart (
    .pclk(pclk),
    .reset(reset),
    .tx_start(tx_start),
    .data_in(data_in),
    .tx_line(tx_line),
    .tx_busy(tx_busy),
    .rx_serial(rx_serial),
    .rx_data(rx_data),
    .rx_done(rx_done)
  );

  // Clock generation
  initial begin
    pclk = 0;
    forever #5 pclk = ~pclk; // Generate a 100 MHz clock (10ns period)
  end

  // Simulate external RX line (loopback from TX line for testing)
  // In a real test, rx_serial would be driven by another source
  always @* begin
    rx_serial <= tx_line; // Use non-blocking assignment for proper simulation behavior
  end

  // Test sequence
  initial begin
    $dumpfile("uart.vcd");  // For waveform viewing
    $dumpvars(0, uart);

    // Initialize signals
    reset = 1;
    tx_start = 0;
    data_in = 8'h00;
    rx_serial = 1; // Idle state is high for UART

    // Reset sequence
    #100; // Wait 100 ns for global reset
    reset = 0; // Release reset
    
    // Wait for a few clock cycles after reset
    #20;

    // Transmit a byte
    data_in = 8'hA5; // Example data to transmit
    tx_start = 1;
    #10; // Hold start for one clock cycle
    tx_start = 0;

    // Wait until a byte is received
    wait (rx_done);
    #30; // Wait a bit more for any additional logic

    // Check if received data matches transmitted data
    if (rx_data == data_in) begin
      $display("Test Passed: Data transmitted and received correctly.");
    end else begin
      $display("Test Failed: Received data: %02h, Expected data: %02h", rx_data, data_in);
    end

    // Finish the test
    $finish;
  end

endmodule

uart/uart.vcd
$date
	Fri Nov 17 22:22:00 2023
$end
$version
	Icarus Verilog
$end
$timescale
	1ps
$end
$scope module uart_tb $end
$scope module uart $end
$var wire 8 ! data_in [7:0] $end
$var wire 1 " pclk $end
$var wire 1 # reset $end
$var wire 1 $ rx_serial $end
$var wire 1 % tx_start $end
$var wire 1 & tx_line $end
$var wire 1 ' tx_busy $end
$var wire 1 ( rx_done $end
$var wire 8 ) rx_data [7:0] $end
$var wire 1 * framing_error $end
$var wire 1 + clk_tx $end
$var wire 1 , clk_rcvr $end
$var parameter 32 - BAUD_RATE $end
$var parameter 32 . CLOCK_RATE $end
$scope module baud_gen $end
$var wire 1 " clk $end
$var wire 1 # reset $end
$var parameter 32 / BAUD_RATE $end
$var parameter 32 0 CLOCK_RATE $end
$var parameter 64 1 MAX_RATE_RX $end
$var parameter 64 2 MAX_RATE_TX $end
$var parameter 32 3 RX_CNT_WIDTH $end
$var parameter 32 4 TX_CNT_WIDTH $end
$var reg 1 , clk_rcvr $end
$var reg 1 + clk_tx $end
$var reg 3 5 counter_rcvr [2:0] $end
$var reg 7 6 counter_tx [6:0] $end
$upscope $end
$scope module rx_uut $end
$var wire 1 # reset $end
$var wire 1 , rx_clk $end
$var wire 1 $ rx_serial $end
$var parameter 32 7 SAMPLES_PER_BIT $end
$var parameter 32 8 SAMPLE_POINT $end
$var reg 4 9 bit_index [3:0] $end
$var reg 1 * framing_error $end
$var reg 8 : rx_data [7:0] $end
$var reg 1 ( rx_done $end
$var reg 4 ; sample_count [3:0] $end
$var reg 8 < shift_reg [7:0] $end
$var reg 3 = state [2:0] $end
$upscope $end
$scope module tx_uut $end
$var wire 1 + clk $end
$var wire 8 > data_in [7:0] $end
$var wire 1 # reset $end
$var wire 1 % tx_start $end
$var reg 3 ? Dctr [2:0] $end
$var reg 3 @ state [2:0] $end
$var reg 1 ' tx_busy $end
$var reg 1 & tx_line $end
$upscope $end
$upscope $end
$upscope $end
$enddefinitions $end
$comment Show the parameter values. $end
$dumpall
b111 8
b1111 7
b111 4
b11 3
b1101000 2
b110 1
b101111101011110000100000000 0
b10010110000000 /
b101111101011110000100000000 .
b10010110000000 -
$end
#0
$dumpvars
b0 @
b0 ?
b0 >
b0 =
b0 <
b0 ;
b0 :
b0 9
b0 6
b0 5
0,
0+
0*
b0 )
0(
0'
1&
0%
1$
1#
0"
b0 !
$end
#5000
1"
#10000
0"
#15000
1"
#20000
0"
#25000
1"
#30000
0"
#35000
1"
#40000
0"
#45000
1"
#50000
0"
#55000
1"
#60000
0"
#65000
1"
#70000
0"
#75000
1"
#80000
0"
#85000
1"
#90000
0"
#95000
1"
#100000
0"
0#
#105000
b1 5
b1 6
1"
#110000
0"
#115000
b10 5
b10 6
1"
#120000
0$
1'
0&
b1 @
0"
1%
b10100101 !
b10100101 >
#125000
b11 5
b11 6
1"
#130000
0"
0%
#135000
b100 5
b100 6
1"
#140000
0"
#145000
b101 5
b101 6
1"
#150000
0"
#155000
b110 5
b110 6
1"
#160000
0"
#165000
b1 =
1,
b0 5
1"
#170000
0"
#175000
b1 5
b111 6
1"
#180000
0"
#185000
b10 5
b1000 6
1"
#190000
0"
#195000
b11 5
b1001 6
1"
#200000
0"
#205000
b100 5
b1010 6
1"
#210000
0"
#215000
b101 5
b1011 6
1"
#220000
0"
#225000
b110 5
b1100 6
1"
#230000
0"
#235000
0,
b0 5
1"
#240000
0"
#245000
b1 5
b1101 6
1"
#250000
0"
#255000
b10 5
b1110 6
1"
#260000
0"
#265000
b11 5
b1111 6
1"
#270000
0"
#275000
b100 5
b10000 6
1"
#280000
0"
#285000
b101 5
b10001 6
1"
#290000
0"
#295000
b110 5
b10010 6
1"
#300000
0"
#305000
b1 ;
1,
b0 5
1"
#310000
0"
#315000
b1 5
b10011 6
1"
#320000
0"
#325000
b10 5
b10100 6
1"
#330000
0"
#335000
b11 5
b10101 6
1"
#340000
0"
#345000
b100 5
b10110 6
1"
#350000
0"
#355000
b101 5
b10111 6
1"
#360000
0"
#365000
b110 5
b11000 6
1"
#370000
0"
#375000
0,
b0 5
1"
#380000
0"
#385000
b1 5
b11001 6
1"
#390000
0"
#395000
b10 5
b11010 6
1"
#400000
0"
#405000
b11 5
b11011 6
1"
#410000
0"
#415000
b100 5
b11100 6
1"
#420000
0"
#425000
b101 5
b11101 6
1"
#430000
0"
#435000
b110 5
b11110 6
1"
#440000
0"
#445000
b10 ;
1,
b0 5
1"
#450000
0"
#455000
b1 5
b11111 6
1"
#460000
0"
#465000
b10 5
b100000 6
1"
#470000
0"
#475000
b11 5
b100001 6
1"
#480000
0"
#485000
b100 5
b100010 6
1"
#490000
0"
#495000
b101 5
b100011 6
1"
#500000
0"
#505000
b110 5
b100100 6
1"
#510000
0"
#515000
0,
b0 5
1"
#520000
0"
#525000
b1 5
b100101 6
1"
#530000
0"
#535000
b10 5
b100110 6
1"
#540000
0"
#545000
b11 5
b100111 6
1"
#550000
0"
#555000
b100 5
b101000 6
1"
#560000
0"
#565000
b101 5
b101001 6
1"
#570000
0"
#575000
b110 5
b101010 6
1"
#580000
0"
#585000
b11 ;
1,
b0 5
1"
#590000
0"
#595000
b1 5
b101011 6
1"
#600000
0"
#605000
b10 5
b101100 6
1"
#610000
0"
#615000
b11 5
b101101 6
1"
#620000
0"
#625000
b100 5
b101110 6
1"
#630000
0"
#635000
b101 5
b101111 6
1"
#640000
0"
#645000
b110 5
b110000 6
1"
#650000
0"
#655000
0,
b0 5
1"
#660000
0"
#665000
b1 5
b110001 6
1"
#670000
0"
#675000
b10 5
b110010 6
1"
#680000
0"
#685000
b11 5
b110011 6
1"
#690000
0"
#695000
b100 5
b110100 6
1"
#700000
0"
#705000
b101 5
b110101 6
1"
#710000
0"
#715000
b110 5
b110110 6
1"
#720000
0"
#725000
b100 ;
1,
b0 5
1"
#730000
0"
#735000
b1 5
b110111 6
1"
#740000
0"
#745000
b10 5
b111000 6
1"
#750000
0"
#755000
b11 5
b111001 6
1"
#760000
0"
#765000
b100 5
b111010 6
1"
#770000
0"
#775000
b101 5
b111011 6
1"
#780000
0"
#785000
b110 5
b111100 6
1"
#790000
0"
#795000
0,
b0 5
1"
#800000
0"
#805000
b1 5
b111101 6
1"
#810000
0"
#815000
b10 5
b111110 6
1"
#820000
0"
#825000
b11 5
b111111 6
1"
#830000
0"
#835000
b100 5
b1000000 6
1"
#840000
0"
#845000
b101 5
b1000001 6
1"
#850000
0"
#855000
b110 5
b1000010 6
1"
#860000
0"
#865000
b101 ;
1,
b0 5
1"
#870000
0"
#875000
b1 5
b1000011 6
1"
#880000
0"
#885000
b10 5
b1000100 6
1"
#890000
0"
#895000
b11 5
b1000101 6
1"
#900000
0"
#905000
b100 5
b1000110 6
1"
#910000
0"
#915000
b101 5
b1000111 6
1"
#920000
0"
#925000
b110 5
b1001000 6
1"
#930000
0"
#935000
0,
b0 5
1"
#940000
0"
#945000
b1 5
b1001001 6
1"
#950000
0"
#955000
b10 5
b1001010 6
1"
#960000
0"
#965000
b11 5
b1001011 6
1"
#970000
0"
#975000
b100 5
b1001100 6
1"
#980000
0"
#985000
b101 5
b1001101 6
1"
#990000
0"
#995000
b110 5
b1001110 6
1"
#1000000
0"
#1005000
b110 ;
1,
b0 5
1"
#1010000
0"
#1015000
b1 5
b1001111 6
1"
#1020000
0"
#1025000
b10 5
b1010000 6
1"
#1030000
0"
#1035000
b11 5
b1010001 6
1"
#1040000
0"
#1045000
b100 5
b1010010 6
1"
#1050000
0"
#1055000
b101 5
b1010011 6
1"
#1060000
0"
#1065000
b110 5
b1010100 6
1"
#1070000
0"
#1075000
0,
b0 5
1"
#1080000
0"
#1085000
b1 5
b1010101 6
1"
#1090000
0"
#1095000
b10 5
b1010110 6
1"
#1100000
0"
#1105000
b11 5
b1010111 6
1"
#1110000
0"
#1115000
b100 5
b1011000 6
1"
#1120000
0"
#1125000
b101 5
b1011001 6
1"
#1130000
0"
#1135000
b110 5
b1011010 6
1"
#1140000
0"
#1145000
b111 ;
1,
b0 5
1"
#1150000
0"
#1155000
b1 5
b1011011 6
1"
#1160000
0"
#1165000
b10 5
b1011100 6
1"
#1170000
0"
#1175000
b11 5
b1011101 6
1"
#1180000
0"
#1185000
b100 5
b1011110 6
1"
#1190000
0"
#1195000
b101 5
b1011111 6
1"
#1200000
0"
#1205000
b110 5
b1100000 6
1"
#1210000
0"
#1215000
0,
b0 5
1"
#1220000
0"
#1225000
b1 5
b1100001 6
1"
#1230000
0"
#1235000
b10 5
b1100010 6
1"
#1240000
0"
#1245000
b11 5
b1100011 6
1"
#1250000
0"
#1255000
b100 5
b1100100 6
1"
#1260000
0"
#1265000
b101 5
b1100101 6
1"
#1270000
0"
#1275000
b110 5
b1100110 6
1"
#1280000
0"
#1285000
b10 =
b0 ;
1,
b0 5
1"
#1290000
0"
#1295000
b1 5
b1100111 6
1"
#1300000
0"
#1305000
b10 5
b1101000 6
1"
#1310000
0"
#1315000
1$
1&
b10 @
1+
b0 6
1"
#1320000
0"
#1325000
b11 5
b1 6
1"
#1330000
0"
#1335000
b100 5
b10 6
1"
#1340000
0"
#1345000
b101 5
b11 6
1"
#1350000
0"
#1355000
b110 5
b100 6
1"
#1360000
0"
#1365000
0,
b0 5
1"
#1370000
0"
#1375000
b1 5
b101 6
1"
#1380000
0"
#1385000
b10 5
b110 6
1"
#1390000
0"
#1395000
b11 5
b111 6
1"
#1400000
0"
#1405000
b100 5
b1000 6
1"
#1410000
0"
#1415000
b101 5
b1001 6
1"
#1420000
0"
#1425000
b110 5
b1010 6
1"
#1430000
0"
#1435000
b1 ;
1,
b0 5
1"
#1440000
0"
#1445000
b1 5
b1011 6
1"
#1450000
0"
#1455000
b10 5
b1100 6
1"
#1460000
0"
#1465000
b11 5
b1101 6
1"
#1470000
0"
#1475000
b100 5
b1110 6
1"
#1480000
0"
#1485000
b101 5
b1111 6
1"
#1490000
0"
#1495000
b110 5
b10000 6
1"
#1500000
0"
#1505000
0,
b0 5
1"
#1510000
0"
#1515000
b1 5
b10001 6
1"
#1520000
0"
#1525000
b10 5
b10010 6
1"
#1530000
0"
#1535000
b11 5
b10011 6
1"
#1540000
0"
#1545000
b100 5
b10100 6
1"
#1550000
0"
#1555000
b101 5
b10101 6
1"
#1560000
0"
#1565000
b110 5
b10110 6
1"
#1570000
0"
#1575000
b10 ;
1,
b0 5
1"
#1580000
0"
#1585000
b1 5
b10111 6
1"
#1590000
0"
#1595000
b10 5
b11000 6
1"
#1600000
0"
#1605000
b11 5
b11001 6
1"
#1610000
0"
#1615000
b100 5
b11010 6
1"
#1620000
0"
#1625000
b101 5
b11011 6
1"
#1630000
0"
#1635000
b110 5
b11100 6
1"
#1640000
0"
#1645000
0,
b0 5
1"
#1650000
0"
#1655000
b1 5
b11101 6
1"
#1660000
0"
#1665000
b10 5
b11110 6
1"
#1670000
0"
#1675000
b11 5
b11111 6
1"
#1680000
0"
#1685000
b100 5
b100000 6
1"
#1690000
0"
#1695000
b101 5
b100001 6
1"
#1700000
0"
#1705000
b110 5
b100010 6
1"
#1710000
0"
#1715000
b11 ;
1,
b0 5
1"
#1720000
0"
#1725000
b1 5
b100011 6
1"
#1730000
0"
#1735000
b10 5
b100100 6
1"
#1740000
0"
#1745000
b11 5
b100101 6
1"
#1750000
0"
#1755000
b100 5
b100110 6
1"
#1760000
0"
#1765000
b101 5
b100111 6
1"
#1770000
0"
#1775000
b110 5
b101000 6
1"
#1780000
0"
#1785000
0,
b0 5
1"
#1790000
0"
#1795000
b1 5
b101001 6
1"
#1800000
0"
#1805000
b10 5
b101010 6
1"
#1810000
0"
#1815000
b11 5
b101011 6
1"
#1820000
0"
#1825000
b100 5
b101100 6
1"
#1830000
0"
#1835000
b101 5
b101101 6
1"
#1840000
0"
#1845000
b110 5
b101110 6
1"
#1850000
0"
#1855000
b100 ;
1,
b0 5
1"
#1860000
0"
#1865000
b1 5
b101111 6
1"
#1870000
0"
#1875000
b10 5
b110000 6
1"
#1880000
0"
#1885000
b11 5
b110001 6
1"
#1890000
0"
#1895000
b100 5
b110010 6
1"
#1900000
0"
#1905000
b101 5
b110011 6
1"
#1910000
0"
#1915000
b110 5
b110100 6
1"
#1920000
0"
#1925000
0,
b0 5
1"
#1930000
0"
#1935000
b1 5
b110101 6
1"
#1940000
0"
#1945000
b10 5
b110110 6
1"
#1950000
0"
#1955000
b11 5
b110111 6
1"
#1960000
0"
#1965000
b100 5
b111000 6
1"
#1970000
0"
#1975000
b101 5
b111001 6
1"
#1980000
0"
#1985000
b110 5
b111010 6
1"
#1990000
0"
#1995000
b101 ;
1,
b0 5
1"
#2000000
0"
#2005000
b1 5
b111011 6
1"
#2010000
0"
#2015000
b10 5
b111100 6
1"
#2020000
0"
#2025000
b11 5
b111101 6
1"
#2030000
0"
#2035000
b100 5
b111110 6
1"
#2040000
0"
#2045000
b101 5
b111111 6
1"
#2050000
0"
#2055000
b110 5
b1000000 6
1"
#2060000
0"
#2065000
0,
b0 5
1"
#2070000
0"
#2075000
b1 5
b1000001 6
1"
#2080000
0"
#2085000
b10 5
b1000010 6
1"
#2090000
0"
#2095000
b11 5
b1000011 6
1"
#2100000
0"
#2105000
b100 5
b1000100 6
1"
#2110000
0"
#2115000
b101 5
b1000101 6
1"
#2120000
0"
#2125000
b110 5
b1000110 6
1"
#2130000
0"
#2135000
b110 ;
1,
b0 5
1"
#2140000
0"
#2145000
b1 5
b1000111 6
1"
#2150000
0"
#2155000
b10 5
b1001000 6
1"
#2160000
0"
#2165000
b11 5
b1001001 6
1"
#2170000
0"
#2175000
b100 5
b1001010 6
1"
#2180000
0"
#2185000
b101 5
b1001011 6
1"
#2190000
0"
#2195000
b110 5
b1001100 6
1"
#2200000
0"
#2205000
0,
b0 5
1"
#2210000
0"
#2215000
b1 5
b1001101 6
1"
#2220000
0"
#2225000
b10 5
b1001110 6
1"
#2230000
0"
#2235000
b11 5
b1001111 6
1"
#2240000
0"
#2245000
b100 5
b1010000 6
1"
#2250000
0"
#2255000
b101 5
b1010001 6
1"
#2260000
0"
#2265000
b110 5
b1010010 6
1"
#2270000
0"
#2275000
b111 ;
1,
b0 5
1"
#2280000
0"
#2285000
b1 5
b1010011 6
1"
#2290000
0"
#2295000
b10 5
b1010100 6
1"
#2300000
0"
#2305000
b11 5
b1010101 6
1"
#2310000
0"
#2315000
b100 5
b1010110 6
1"
#2320000
0"
#2325000
b101 5
b1010111 6
1"
#2330000
0"
#2335000
b110 5
b1011000 6
1"
#2340000
0"
#2345000
0,
b0 5
1"
#2350000
0"
#2355000
b1 5
b1011001 6
1"
#2360000
0"
#2365000
b10 5
b1011010 6
1"
#2370000
0"
#2375000
b11 5
b1011011 6
1"
#2380000
0"
#2385000
b100 5
b1011100 6
1"
#2390000
0"
#2395000
b101 5
b1011101 6
1"
#2400000
0"
#2405000
b110 5
b1011110 6
1"
#2410000
0"
#2415000
b1000 ;
1,
b0 5
1"
#2420000
0"
#2425000
b1 5
b1011111 6
1"
#2430000
0"
#2435000
b10 5
b1100000 6
1"
#2440000
0"
#2445000
b11 5
b1100001 6
1"
#2450000
0"
#2455000
b100 5
b1100010 6
1"
#2460000
0"
#2465000
b101 5
b1100011 6
1"
#2470000
0"
#2475000
b110 5
b1100100 6
1"
#2480000
0"
#2485000
0,
b0 5
1"
#2490000
0"
#2495000
b1 5
b1100101 6
1"
#2500000
0"
#2505000
b10 5
b1100110 6
1"
#2510000
0"
#2515000
b11 5
b1100111 6
1"
#2520000
0"
#2525000
b100 5
b1101000 6
1"
#2530000
0"
#2535000
0+
b0 6
1"
#2540000
0"
#2545000
b101 5
b1 6
1"
#2550000
0"
#2555000
b110 5
b10 6
1"
#2560000
0"
#2565000
b1001 ;
1,
b0 5
1"
#2570000
0"
#2575000
b1 5
b11 6
1"
#2580000
0"
#2585000
b10 5
b100 6
1"
#2590000
0"
#2595000
b11 5
b101 6
1"
#2600000
0"
#2605000
b100 5
b110 6
1"
#2610000
0"
#2615000
b101 5
b111 6
1"
#2620000
0"
#2625000
b110 5
b1000 6
1"
#2630000
0"
#2635000
0,
b0 5
1"
#2640000
0"
#2645000
b1 5
b1001 6
1"
#2650000
0"
#2655000
b10 5
b1010 6
1"
#2660000
0"
#2665000
b11 5
b1011 6
1"
#2670000
0"
#2675000
b100 5
b1100 6
1"
#2680000
0"
#2685000
b101 5
b1101 6
1"
#2690000
0"
#2695000
b110 5
b1110 6
1"
#2700000
0"
#2705000
b1010 ;
1,
b0 5
1"
#2710000
0"
#2715000
b1 5
b1111 6
1"
#2720000
0"
#2725000
b10 5
b10000 6
1"
#2730000
0"
#2735000
b11 5
b10001 6
1"
#2740000
0"
#2745000
b100 5
b10010 6
1"
#2750000
0"
#2755000
b101 5
b10011 6
1"
#2760000
0"
#2765000
b110 5
b10100 6
1"
#2770000
0"
#2775000
0,
b0 5
1"
#2780000
0"
#2785000
b1 5
b10101 6
1"
#2790000
0"
#2795000
b10 5
b10110 6
1"
#2800000
0"
#2805000
b11 5
b10111 6
1"
#2810000
0"
#2815000
b100 5
b11000 6
1"
#2820000
0"
#2825000
b101 5
b11001 6
1"
#2830000
0"
#2835000
b110 5
b11010 6
1"
#2840000
0"
#2845000
b1011 ;
1,
b0 5
1"
#2850000
0"
#2855000
b1 5
b11011 6
1"
#2860000
0"
#2865000
b10 5
b11100 6
1"
#2870000
0"
#2875000
b11 5
b11101 6
1"
#2880000
0"
#2885000
b100 5
b11110 6
1"
#2890000
0"
#2895000
b101 5
b11111 6
1"
#2900000
0"
#2905000
b110 5
b100000 6
1"
#2910000
0"
#2915000
0,
b0 5
1"
#2920000
0"
#2925000
b1 5
b100001 6
1"
#2930000
0"
#2935000
b10 5
b100010 6
1"
#2940000
0"
#2945000
b11 5
b100011 6
1"
#2950000
0"
#2955000
b100 5
b100100 6
1"
#2960000
0"
#2965000
b101 5
b100101 6
1"
#2970000
0"
#2975000
b110 5
b100110 6
1"
#2980000
0"
#2985000
b1100 ;
1,
b0 5
1"
#2990000
0"
#2995000
b1 5
b100111 6
1"
#3000000
0"
#3005000
b10 5
b101000 6
1"
#3010000
0"
#3015000
b11 5
b101001 6
1"
#3020000
0"
#3025000
b100 5
b101010 6
1"
#3030000
0"
#3035000
b101 5
b101011 6
1"
#3040000
0"
#3045000
b110 5
b101100 6
1"
#3050000
0"
#3055000
0,
b0 5
1"
#3060000
0"
#3065000
b1 5
b101101 6
1"
#3070000
0"
#3075000
b10 5
b101110 6
1"
#3080000
0"
#3085000
b11 5
b101111 6
1"
#3090000
0"
#3095000
b100 5
b110000 6
1"
#3100000
0"
#3105000
b101 5
b110001 6
1"
#3110000
0"
#3115000
b110 5
b110010 6
1"
#3120000
0"
#3125000
b1101 ;
1,
b0 5
1"
#3130000
0"
#3135000
b1 5
b110011 6
1"
#3140000
0"
#3145000
b10 5
b110100 6
1"
#3150000
0"
#3155000
b11 5
b110101 6
1"
#3160000
0"
#3165000
b100 5
b110110 6
1"
#3170000
0"
#3175000
b101 5
b110111 6
1"
#3180000
0"
#3185000
b110 5
b111000 6
1"
#3190000
0"
#3195000
0,
b0 5
1"
#3200000
0"
#3205000
b1 5
b111001 6
1"
#3210000
0"
#3215000
b10 5
b111010 6
1"
#3220000
0"
#3225000
b11 5
b111011 6
1"
